podspy/__init__.py
podspy/logging.json
podspy/discovery/__init__.py
podspy/discovery/alpha/__init__.py
podspy/discovery/alpha/classic.py
podspy/discovery/alpha/plus.py
podspy/graph/__init__.py
podspy/graph/base.py
podspy/graph/constants.py
podspy/graph/directed.py
podspy/graph/utils.py
podspy/graph/drawing/__init__.py
podspy/graph/drawing/ps_agraph.py
podspy/log/__init__.py
podspy/log/constants.py
podspy/log/data_io.py
podspy/log/factory.py
podspy/log/table.py
podspy/log/utils.py
podspy/petrinet/__init__.py
podspy/petrinet/drawing.py
podspy/petrinet/elements.py
podspy/petrinet/factory.py
podspy/petrinet/io.py
podspy/petrinet/nets.py
podspy/petrinet/semantics.py
podspy/petrinet/pnml/__init__.py
podspy/petrinet/pnml/base.py
podspy/petrinet/pnml/elements.py
podspy/petrinet/pnml/extension.py
podspy/petrinet/pnml/factory.py
podspy/petrinet/pnml/graphics.py
podspy/structure/__init__.py
podspy/structure/causal.py
podspy/structure/footprint.py
podspy/utils/__init__.py
podspy/utils/attributes.py
podspy/utils/colors.py
podspy/utils/conversion.py
podspy/utils/layout.py
podspy/utils/multiset.py
podspy/utils/patterns.py
podspy/utils/shapes.py
podspy-0.1.6.dist-info/LICENSE
podspy-0.1.6.dist-info/METADATA
podspy-0.1.6.dist-info/WHEEL
podspy-0.1.6.dist-info/entry_points.txt
podspy-0.1.6.dist-info/top_level.txt
podspy-0.1.6.dist-info/RECORD
