Metadata-Version: 2.1
Name: podspy
Version: 0.1.6
Summary: A SciKit for process oriented data science
Home-page: UNKNOWN
Author: Wai Lam Jonathan Lee
Author-email: walee@uc.cl
License: UNKNOWN
Platform: UNKNOWN
Requires-Dist: numpy (>=1.15.4)
Requires-Dist: pandas (>=0.23.4)
Requires-Dist: opyenxes (>=0.3.0)
Requires-Dist: ciso8601 (>=2.1.1)
Requires-Dist: lxml (>=4.2.5)
Requires-Dist: pygraphviz (>=1.5)
